make87_ntfy/__init__.py
make87_ntfy/publish_pb2.py
make87_ntfy/publish_pb2.pyi
make87_ntfy-0.4.1.dist-info/METADATA
make87_ntfy-0.4.1.dist-info/WHEEL
make87_ntfy-0.4.1.dist-info/top_level.txt
make87_ntfy-0.4.1.dist-info/RECORD
